biquad/__init__.py
biquad/allpass.py
biquad/bandpass.py
biquad/biquad.py
biquad/highpass.py
biquad/highshelf.py
biquad/lowpass.py
biquad/lowshelf.py
biquad/notch.py
biquad/peak.py
biquad-0.4.dist-info/LICENSE
biquad-0.4.dist-info/METADATA
biquad-0.4.dist-info/WHEEL
biquad-0.4.dist-info/top_level.txt
biquad-0.4.dist-info/RECORD
