Metadata-Version: 2.1
Name: biquad
Version: 0.4
Summary: Collection of alterable digital biquad filters for dynamic audio effect creation
Home-page: https://github.com/jurihock/biquad
Author: Juergen Hock
Author-email: juergen.hock@jurihock.de
License: MIT
Keywords: digital,audio,signal,processing,dasp,dafx,effects,filter,equalizer,eq,biquad,frequency,phase,spectrum,algorithms,analysis,synthesis,c,cpp,python
Classifier: Intended Audience :: Developers
Classifier: Intended Audience :: Education
Classifier: Intended Audience :: Other Audience
Classifier: Intended Audience :: Science/Research
Classifier: License :: OSI Approved :: MIT License
Classifier: Programming Language :: C
Classifier: Programming Language :: C++
Classifier: Programming Language :: Python :: 3
Classifier: Topic :: Artistic Software
Classifier: Topic :: Education
Classifier: Topic :: Multimedia :: Sound/Audio
Classifier: Topic :: Multimedia :: Sound/Audio :: Analysis
Classifier: Topic :: Multimedia :: Sound/Audio :: Sound Synthesis
Classifier: Topic :: Scientific/Engineering
Classifier: Topic :: Software Development :: Libraries
Requires-Python: >=3
License-File: LICENSE
Requires-Dist: numba
Requires-Dist: numpy
Provides-Extra: plot
Requires-Dist: matplotlib ; extra == 'plot'
